{
  "code": 0,
  "summary": {
    "cost": 6640,
    "routes": 1,
    "unassigned": 0,
    "setup": 0,
    "service": 0,
    "duration": 6640,
    "waiting_time": 0,
    "priority": 0,
    "violations": [],
    "computing_times": {
      "loading": 1393,
      "solving": 3,
      "routing": 0
    }
  },
  "unassigned": [],
  "routes": [
    {
      "vehicle": 2,
      "cost": 6640,
      "setup": 0,
      "service": 0,
      "duration": 6640,
      "waiting_time": 0,
      "priority": 0,
      "steps": [
        {
          "type": "start",
          "location": [
            78.17611956533857,
            11.683720337350456
          ],
          "setup": 0,
          "service": 0,
          "waiting_time": 0,
          "arrival": 0,
          "duration": 0,
          "violations": []
        },
        {
          "type": "job",
          "location": [
            78.17642282040464,
            11.6856184753304
          ],
          "id": 41,
          "setup": 0,
          "service": 0,
          "waiting_time": 0,
          "job": 41,
          "arrival": 32,
          "duration": 32,
          "violations": []
        },
        {
          "type": "job",
          "location": [
            78.18638175584711,
            11.68740894028765
          ],
          "id": 1,
          "setup": 0,
          "service": 0,
          "waiting_time": 0,
          "job": 1,
          "arrival": 196,
          "duration": 196,
          "violations": []
        },
        {
          "type": "job",
          "location": [
            78.18306227345555,
            11.68973553969939
          ],
          "id": 44,
          "setup": 0,
          "service": 0,
          "waiting_time": 0,
          "job": 44,
          "arrival": 315,
          "duration": 315,
          "violations": []
        },
        {
          "type": "job",
          "location": [
            78.1829995274735,
            11.69028256145346
          ],
          "id": 22,
          "setup": 0,
          "service": 0,
          "waiting_time": 0,
          "job": 22,
          "arrival": 387,
          "duration": 387,
          "violations": []
        },
        {
          "type": "job",
          "location": [
            78.19224793593735,
            11.6916181730301
          ],
          "id": 29,
          "setup": 0,
          "service": 0,
          "waiting_time": 0,
          "job": 29,
          "arrival": 525,
          "duration": 525,
          "violations": []
        },
        {
          "type": "job",
          "location": [
            78.17512832395745,
            11.68039770932664
          ],
          "id": 7,
          "setup": 0,
          "service": 0,
          "waiting_time": 0,
          "job": 7,
          "arrival": 751,
          "duration": 751,
          "violations": []
        },
        {
          "type": "job",
          "location": [
            78.17115757414206,
            11.67029630112193
          ],
          "id": 16,
          "setup": 0,
          "service": 0,
          "waiting_time": 0,
          "job": 16,
          "arrival": 945,
          "duration": 945,
          "violations": []
        },
        {
          "type": "job",
          "location": [
            78.16765470117699,
            11.67503761010994
          ],
          "id": 45,
          "setup": 0,
          "service": 0,
          "waiting_time": 0,
          "job": 45,
          "arrival": 1215,
          "duration": 1215,
          "violations": []
        },
        {
          "type": "job",
          "location": [
            78.17031688243529,
            11.67748987783772
          ],
          "id": 27,
          "setup": 0,
          "service": 0,
          "waiting_time": 0,
          "job": 27,
          "arrival": 1317,
          "duration": 1317,
          "violations": []
        },
        {
          "type": "job",
          "location": [
            78.17076722859233,
            11.67818072353824
          ],
          "id": 8,
          "setup": 0,
          "service": 0,
          "waiting_time": 0,
          "job": 8,
          "arrival": 1441,
          "duration": 1441,
          "violations": []
        },
        {
          "type": "job",
          "location": [
            78.17011819376076,
            11.68137463765541
          ],
          "id": 43,
          "setup": 0,
          "service": 0,
          "waiting_time": 0,
          "job": 43,
          "arrival": 1580,
          "duration": 1580,
          "violations": []
        },
        {
          "type": "job",
          "location": [
            78.17409390762457,
            11.68520243673543
          ],
          "id": 31,
          "setup": 0,
          "service": 0,
          "waiting_time": 0,
          "job": 31,
          "arrival": 1681,
          "duration": 1681,
          "violations": []
        },
        {
          "type": "job",
          "location": [
            78.17205663138502,
            11.68510416326842
          ],
          "id": 33,
          "setup": 0,
          "service": 0,
          "waiting_time": 0,
          "job": 33,
          "arrival": 1783,
          "duration": 1783,
          "violations": []
        },
        {
          "type": "job",
          "location": [
            78.17079230201486,
            11.68928737358011
          ],
          "id": 35,
          "setup": 0,
          "service": 0,
          "waiting_time": 0,
          "job": 35,
          "arrival": 1967,
          "duration": 1967,
          "violations": []
        },
        {
          "type": "job",
          "location": [
            78.17857736116869,
            11.68767878908736
          ],
          "id": 14,
          "setup": 0,
          "service": 0,
          "waiting_time": 0,
          "job": 14,
          "arrival": 2141,
          "duration": 2141,
          "violations": []
        },
        {
          "type": "job",
          "location": [
            78.17838966349719,
            11.68691555368117
          ],
          "id": 30,
          "setup": 0,
          "service": 0,
          "waiting_time": 0,
          "job": 30,
          "arrival": 2141,
          "duration": 2141,
          "violations": []
        },
        {
          "type": "job",
          "location": [
            78.17864511203769,
            11.70881014711377
          ],
          "id": 36,
          "setup": 0,
          "service": 0,
          "waiting_time": 0,
          "job": 36,
          "arrival": 2325,
          "duration": 2325,
          "violations": []
        },
        {
          "type": "job",
          "location": [
            78.17303549172291,
            11.70589621177907
          ],
          "id": 6,
          "setup": 0,
          "service": 0,
          "waiting_time": 0,
          "job": 6,
          "arrival": 2445,
          "duration": 2445,
          "violations": []
        },
        {
          "type": "job",
          "location": [
            78.1632621133048,
            11.72520908658909
          ],
          "id": 2,
          "setup": 0,
          "service": 0,
          "waiting_time": 0,
          "job": 2,
          "arrival": 2754,
          "duration": 2754,
          "violations": []
        },
        {
          "type": "job",
          "location": [
            78.16213339142955,
            11.70077809447231
          ],
          "id": 46,
          "setup": 0,
          "service": 0,
          "waiting_time": 0,
          "job": 46,
          "arrival": 3105,
          "duration": 3105,
          "violations": []
        },
        {
          "type": "job",
          "location": [
            78.16431269113723,
            11.69968537481385
          ],
          "id": 24,
          "setup": 0,
          "service": 0,
          "waiting_time": 0,
          "job": 24,
          "arrival": 3146,
          "duration": 3146,
          "violations": []
        },
        {
          "type": "job",
          "location": [
            78.1613661853604,
            11.69849139638221
          ],
          "id": 10,
          "setup": 0,
          "service": 0,
          "waiting_time": 0,
          "job": 10,
          "arrival": 3183,
          "duration": 3183,
          "violations": []
        },
        {
          "type": "job",
          "location": [
            78.16264941591261,
            11.69871035032834
          ],
          "id": 19,
          "setup": 0,
          "service": 0,
          "waiting_time": 0,
          "job": 19,
          "arrival": 3189,
          "duration": 3189,
          "violations": []
        },
        {
          "type": "job",
          "location": [
            78.16220280563192,
            11.69960097016176
          ],
          "id": 47,
          "setup": 0,
          "service": 0,
          "waiting_time": 0,
          "job": 47,
          "arrival": 3221,
          "duration": 3221,
          "violations": []
        },
        {
          "type": "job",
          "location": [
            78.16060122461028,
            11.69922675296457
          ],
          "id": 49,
          "setup": 0,
          "service": 0,
          "waiting_time": 0,
          "job": 49,
          "arrival": 3254,
          "duration": 3254,
          "violations": []
        },
        {
          "type": "job",
          "location": [
            78.16004641762318,
            11.70279666194502
          ],
          "id": 13,
          "setup": 0,
          "service": 0,
          "waiting_time": 0,
          "job": 13,
          "arrival": 3359,
          "duration": 3359,
          "violations": []
        },
        {
          "type": "job",
          "location": [
            78.15949785888881,
            11.70076688004796
          ],
          "id": 34,
          "setup": 0,
          "service": 0,
          "waiting_time": 0,
          "job": 34,
          "arrival": 3412,
          "duration": 3412,
          "violations": []
        },
        {
          "type": "job",
          "location": [
            78.16044525822637,
            11.69818309555953
          ],
          "id": 5,
          "setup": 0,
          "service": 0,
          "waiting_time": 0,
          "job": 5,
          "arrival": 3471,
          "duration": 3471,
          "violations": []
        },
        {
          "type": "job",
          "location": [
            78.15873813890576,
            11.69664731567291
          ],
          "id": 40,
          "setup": 0,
          "service": 0,
          "waiting_time": 0,
          "job": 40,
          "arrival": 3527,
          "duration": 3527,
          "violations": []
        },
        {
          "type": "job",
          "location": [
            78.15940432163808,
            11.69635945500156
          ],
          "id": 37,
          "setup": 0,
          "service": 0,
          "waiting_time": 0,
          "job": 37,
          "arrival": 3531,
          "duration": 3531,
          "violations": []
        },
        {
          "type": "job",
          "location": [
            78.16005772993954,
            11.69607752145734
          ],
          "id": 21,
          "setup": 0,
          "service": 0,
          "waiting_time": 0,
          "job": 21,
          "arrival": 3550,
          "duration": 3550,
          "violations": []
        },
        {
          "type": "job",
          "location": [
            78.16055750730153,
            11.69562622897759
          ],
          "id": 4,
          "setup": 0,
          "service": 0,
          "waiting_time": 0,
          "job": 4,
          "arrival": 3583,
          "duration": 3583,
          "violations": []
        },
        {
          "type": "job",
          "location": [
            78.15661746364152,
            11.69690875302708
          ],
          "id": 39,
          "setup": 0,
          "service": 0,
          "waiting_time": 0,
          "job": 39,
          "arrival": 3698,
          "duration": 3698,
          "violations": []
        },
        {
          "type": "job",
          "location": [
            78.16185777839337,
            11.69835650052624
          ],
          "id": 11,
          "setup": 0,
          "service": 0,
          "waiting_time": 0,
          "job": 11,
          "arrival": 3877,
          "duration": 3877,
          "violations": []
        },
        {
          "type": "job",
          "location": [
            78.16777329408208,
            11.69784668085145
          ],
          "id": 9,
          "setup": 0,
          "service": 0,
          "waiting_time": 0,
          "job": 9,
          "arrival": 4039,
          "duration": 4039,
          "violations": []
        },
        {
          "type": "job",
          "location": [
            78.16515384208623,
            11.69695619468971
          ],
          "id": 48,
          "setup": 0,
          "service": 0,
          "waiting_time": 0,
          "job": 48,
          "arrival": 4104,
          "duration": 4104,
          "violations": []
        },
        {
          "type": "job",
          "location": [
            78.16587437021607,
            11.69863127571119
          ],
          "id": 25,
          "setup": 0,
          "service": 0,
          "waiting_time": 0,
          "job": 25,
          "arrival": 4142,
          "duration": 4142,
          "violations": []
        },
        {
          "type": "job",
          "location": [
            78.16531778492617,
            11.70113306646538
          ],
          "id": 20,
          "setup": 0,
          "service": 0,
          "waiting_time": 0,
          "job": 20,
          "arrival": 4211,
          "duration": 4211,
          "violations": []
        },
        {
          "type": "job",
          "location": [
            78.16724761029134,
            11.70249780853362
          ],
          "id": 28,
          "setup": 0,
          "service": 0,
          "waiting_time": 0,
          "job": 28,
          "arrival": 4274,
          "duration": 4274,
          "violations": []
        },
        {
          "type": "job",
          "location": [
            78.16800470002988,
            11.70221872069496
          ],
          "id": 15,
          "setup": 0,
          "service": 0,
          "waiting_time": 0,
          "job": 15,
          "arrival": 4360,
          "duration": 4360,
          "violations": []
        },
        {
          "type": "job",
          "location": [
            78.16712049242796,
            11.70684267380894
          ],
          "id": 17,
          "setup": 0,
          "service": 0,
          "waiting_time": 0,
          "job": 17,
          "arrival": 4506,
          "duration": 4506,
          "violations": []
        },
        {
          "type": "job",
          "location": [
            78.1650489999,
            11.70587047069671
          ],
          "id": 12,
          "setup": 0,
          "service": 0,
          "waiting_time": 0,
          "job": 12,
          "arrival": 4580,
          "duration": 4580,
          "violations": []
        },
        {
          "type": "job",
          "location": [
            78.15951926629621,
            11.70450296797776
          ],
          "id": 23,
          "setup": 0,
          "service": 0,
          "waiting_time": 0,
          "job": 23,
          "arrival": 4779,
          "duration": 4779,
          "violations": []
        },
        {
          "type": "job",
          "location": [
            78.15828021171912,
            11.70664651296812
          ],
          "id": 3,
          "setup": 0,
          "service": 0,
          "waiting_time": 0,
          "job": 3,
          "arrival": 4851,
          "duration": 4851,
          "violations": []
        },
        {
          "type": "job",
          "location": [
            78.15478133915887,
            11.7050442126742
          ],
          "id": 26,
          "setup": 0,
          "service": 0,
          "waiting_time": 0,
          "job": 26,
          "arrival": 5057,
          "duration": 5057,
          "violations": []
        },
        {
          "type": "job",
          "location": [
            78.1575060676265,
            11.70435650060343
          ],
          "id": 50,
          "setup": 0,
          "service": 0,
          "waiting_time": 0,
          "job": 50,
          "arrival": 5210,
          "duration": 5210,
          "violations": []
        },
        {
          "type": "job",
          "location": [
            78.1552188440062,
            11.70016438259525
          ],
          "id": 18,
          "setup": 0,
          "service": 0,
          "waiting_time": 0,
          "job": 18,
          "arrival": 5344,
          "duration": 5344,
          "violations": []
        },
        {
          "type": "job",
          "location": [
            78.153948350261,
            11.70095066557666
          ],
          "id": 38,
          "setup": 0,
          "service": 0,
          "waiting_time": 0,
          "job": 38,
          "arrival": 5404,
          "duration": 5404,
          "violations": []
        },
        {
          "type": "job",
          "location": [
            78.14995153255083,
            11.70175941145178
          ],
          "id": 32,
          "setup": 0,
          "service": 0,
          "waiting_time": 0,
          "job": 32,
          "arrival": 5768,
          "duration": 5768,
          "violations": []
        },
        {
          "type": "job",
          "location": [
            78.15015539550024,
            11.70535285879944
          ],
          "id": 42,
          "setup": 0,
          "service": 0,
          "waiting_time": 0,
          "job": 42,
          "arrival": 6039,
          "duration": 6039,
          "violations": []
        },
        {
          "type": "end",
          "location": [
            78.15988980734215,
            11.675583838261142
          ],
          "setup": 0,
          "service": 0,
          "waiting_time": 0,
          "arrival": 6640,
          "duration": 6640,
          "violations": []
        }
      ],
      "violations": []
    }
  ]
}